olap3-0.1.1-py3.11-nspkg.pth
olap/MDXLexer.g
olap/MDXParser.g
olap/MDXTree.g
olap/interfaces.py
olap/rest/__init__.py
olap/rest/pyramid.py
olap/xmla/__init__.py
olap/xmla/connection.py
olap/xmla/formatreader.py
olap/xmla/interfaces.py
olap/xmla/utils.py
olap/xmla/vs.wsdl
olap/xmla/xmla.py
olap3-0.1.1.dist-info/METADATA
olap3-0.1.1.dist-info/WHEEL
olap3-0.1.1.dist-info/namespace_packages.txt
olap3-0.1.1.dist-info/top_level.txt
olap3-0.1.1.dist-info/RECORD
